Workbook

Sheet Lees mij
A1: Het nac-raamwerk van HuisartsInCijfers — controleversie
A3: Doel: elke stap van de berekening die de site straks toont, als werkende formule. Wijzig een blauw invoergetal en alles rekent door.
A5: LEGENDA
A6: Blauwe tekst = ingevoerd brongetal (met bron en vindplaats in de kolommen ernaast).
A7: Zwarte tekst = formule binnen het blad. Groene tekst = verwijzing naar een ander blad.
A8: Gele vulling = de kernaannames die de uitkomst dragen.
A10: DE ZES AFSPRAKEN (gesprek 7 augustus 2026)
A11: 1. Urenreeks: Nivel-ankerpunten 2018 (49,0) en 2024 (55,7), lineair geinterpoleerd, na 2024 doorgetrokken; dienst op de HAP (2,6 u, meting 2024) gaat er over de hele reeks af.
A12: 2. Drie scope-zuivere niveaus: nac's die de NZa terecht acht -> waarvan in de basistarieven -> waarvan uit tariefgereguleerde tarieven; landelijk via ingeschreven verzekerden.
A13: 3. De tariefketen volgt de verantwoording-2025 (praktijkweging: 2.650, 8,96%, 1,88%), want dat is wat werkelijk in de tarieven zat.
A14: 4. Uitgevraagde uren per fte: 46,2 (NZa-QA 2026, blz. 10); figuur 4.2.6.2 van het feitenrapport geeft 46,5 - tweede vindplaats, niet gebruikt.
A15: 5. Nac-bedrag per jaar = wat in de tarieven van dat jaar zat; 2025 dus de voorcalculatie EUR 202.476.
... A32: Zorgcijfersdatabank / eigen Cijfer-Meester: ingeschreven verzekerden, nac-indexatie, gepubliceerde nac-reeks, CPI (CBS, 2015=100).

Sheet Parameters
A1: Parameters - alle constanten van het raamwerk
A3: Omschrijving | B3: Waarde | C3: Eenheid | D3: Bron | E3: Vindplaats | F3: Status
A4: MODEL PKO 2015 (tariefjaren 2018-2024)
A5: Normpraktijk (patienten per volledige nac, binnen de 100%) | B5: 2095 | C5: patienten | D5: Beleidsregel 2018; PKO 2015 | E5: zorgenz.nl 20-7-2017; tabel 14 en 34 (meting 2.095 +/- 120) | F5: definitief
A6: Aandeel tariefgereguleerd binnen de 100% | B6: 0.7726 | C6: aandeel | D6: PKO 2015 | E6: tabel 33, regel 10 | F6: definitief
A7: Dekking niet-gereguleerd: segment 2 / poh-s / vrij | B7: 0.2274 | C7: aandeel | D7: PKO 2015 | E7: tabel 33 (11,07 + 3,33 + 8,33) | F7: definitief
A8: Nac, prijspeil 2015 | B8: 128311 | C8: euro | D8: PKO 2015 | E8: tabel 34, kolom A | F8: definitief
A9: Praktijkkostenbestanddeel, herijkt, prijspeil 2015 | B9: 182110 | C9: euro | D9: PKO 2015 | E9: tabel 34 | F9: definitief
A10: Rekennorm basisconsulten per fte | B10: 8966 | C10: consulteenheden | D10: PKO 2015 | E10: tabel 17 en 34 | F10: definitief
A11: Fte-definitie: uren per week (cap 1,0) | B11: 40 | C11: uur/week | D11: PKO 2015 | E11: par. 3.2 | F11: definitief
A12: Gemeten werkweek per fte (incl. 2,54 anw) | B12: 52.05 | C12: uur/week | D12: PKO 2015 | E12: blz. 33 | F12: definitief
A14: MODEL PKO 2022 (tariefjaren 2025-2026)
A15: Patienten per fte praktijkhouder (praktijkweging) | B15: 2650 | C15: patienten | D15: Verantwoording 2025 | E15: par. 5.3 (3.672 patienten / 1,39 fte) | F15: definitief
A16: Schoning buiten de 100% | B16: 0.0896 | C16: aandeel | D16: Verantwoording 2025 / PKO 2022 | E16: Tabel 19 / tabel 4.2.6.1; regel: bijlage 8.6.7 | F16: definitief
A17: Correctie poh-ggz (managementtijd) | B17: 0.0188 | C17: aandeel | D17: Verantwoording 2025 / PKO 2022 | E17: Tabel 19 / tabel 4.2.6.1 | F17: afgeleid
A18: Binnen de 100% | B18: =1-B16-B17 -> 0.8916 | C18: aandeel | D18: formule | E18: 1 - schoning - poh-ggz | F18: afgeleid
A19: Normpraktijk-equivalent (patienten per nac binnen 100%) | B19: =B15/B18 -> 2972.1848 | C19: patienten | D19: formule | E19: 2.650 / binnen-100% | F19: afgeleid
A20: Aandeel tariefgereguleerd binnen de 100% | B20: 0.744 | C20: aandeel | D20: Verantwoording 2025 | E20: conform tariefketen (rapport-landelijk: 74,1%, tabel 4.2.1.2) | F20: definitief
A21: Fte-definitie: uren per week (cap 1,0; excl. dienst) | B21: 36 | C21: uur/week | D21: PKO 2022 | E21: bijlage 8.6.7 | F21: definitief
A22: Uitgevraagde uren per fte (NZa) | B22: 46.2 | C22: uur/week | D22: NZa QA 2026 | E22: blz. 10 (figuur 4.2.6.2 rapport: 46,5) | F22: definitief
A23: Nac herijkt (Berenschot), prijspeil 2024 | B23: 194352 | C23: euro | D23: Verantwoording 2025 | E23: functiewaarderingsonderzoek | F23: definitief
A25: ALGEMEEN
A26: Werkweken per jaar (fte-formule NZa) | B26: 46 | C26: weken | D26: NZa | E26: beide modellen, par. 5.3 / 3.2 | F26: definitief
A27: Dienst op de huisartsenpost | B27: 2.6 | C27: uur/week | D27: Nivel 2024 | E27: Flinterman e.a. 2025, blz. 20 | F27: definitief
A28: Nivel-werkweek praktijkhouder, anker 2018 | B28: 49 | C28: uur/week | D28: Nivel | E28: Flinterman e.a. 2025 (reeks 2013/2018/2024) | F28: definitief
A29: Nivel-werkweek praktijkhouder, anker 2024 | B29: 55.7 | C29: uur/week | D29: Nivel 2024 | E29: figuur 18; sms-meting, 884 deelnemers | F29: definitief

Sheet Reeksen
A1: Jaarreeksen - invoer (blauw) en interpolatie (zwart)
A3: Jaar | B3: Ingeschreven verzekerden | C3: status | D3: Nac-bedrag in de tarieven (EUR) | E3: status | F3: Gepubliceerde nac-reeks (Cijfer-Meester) | G3: Praktijkhouders (personen) | H3: herkomst | I3: Werkweek bruto (uur/wk) | J3: Werkweek excl. dienst (uur/wk) | K3: CPI (2015=100) | L3: Winst zelfst. mp, gemiddeld (EUR) | M3: Winst zelfst. mp, mediaan (EUR)
A4: 2018 | B4: 16870343 | C4: definitief | D4: 135397.17 | E4: definitief | F4: 8052 | G4: 7903 | H4: Nivel-beroepenregistratie | I4: =Parameters!$B$28 -> 49 | J4: =I4-Parameters!$B$27 -> 46.4 | K4: 103.44 | L4: 142600 | M4: 133900
A5: 2019 | B5: 16985302 | C5: definitief | D5: 140027.75 | E5: definitief | F5: 8107 | G5: 7873 | H5: Nivel-beroepenregistratie | I5: =ROUND(Parameters!$B$28+(Parameters!$B$29-Parameters!$B$28)*(2019-2018)/6,2) -> 50.12 | J5: =I5-Parameters!$B$27 -> 47.52 | K5: 106.16 | L5: 151400 | M5: 141800
A6: 2020 | B6: 17039624 | C6: definitief | D6: 144620.66 | E6: definitief | F6: 8133 | G6: 7602 | H6: Nivel-beroepenregistratie | I6: =ROUND(Parameters!$B$28+(Parameters!$B$29-Parameters!$B$28)*(2020-2018)/6,2) -> 51.23 | J6: =I6-Parameters!$B$27 -> 48.63 | K6: 107.51 | L6: 164700 | M6: 153400
A7: 2021 | B7: 17136157 | C7: definitief | D7: 147527.54 | E7: definitief | F7: 8179 | G7: 7588 | H7: Nivel-beroepenregistratie | I7: =ROUND(Parameters!$B$28+(Parameters!$B$29-Parameters!$B$28)*(2021-2018)/6,2) -> 52.35 | J7: =I7-Parameters!$B$27 -> 49.75 | K7: 110.39 | L7: 166800 | M7: 153600
A8: 2022 | B8: 17224936 | C8: definitief | D8: 154048.25 | E8: definitief | F8: 8221 | G8: 7585 | H8: Nivel-beroepenregistratie | I8: =ROUND(Parameters!$B$28+(Parameters!$B$29-Parameters!$B$28)*(2022-2018)/6,2) -> 53.47 | J8: =I8-Parameters!$B$27 -> 50.87 | K8: 121.43 | L8: 158600 | M8: 145400
A9: 2023 | B9: 17329993 | C9: definitief | D9: 163845.72 | E9: definitief | F9: 8272 | G9: 7561 | H9: Nivel-beroepenregistratie | I9: =ROUND(Parameters!$B$28+(Parameters!$B$29-Parameters!$B$28)*(2023-2018)/6,2) -> 54.58 | J9: =I9-Parameters!$B$27 -> 51.98 | K9: 126.09 | L9: 173600 | M9: 161300
A10: 2024 | B10: 17399407 | C10: definitief | D10: 171939.7 | E10: schatting (def-index ontbreekt) | F10: 8305 | G10: =ROUND((G9+G11)/2,0) -> 7550 | H10: lineair tussen 2023 en 2025 | I10: =Parameters!$B$29 -> 55.7 | J10: =I10-Parameters!$B$27 -> 53.1 | K10: 130.31
A11: 2025 | B11: 17499537 | C11: schatting | D11: 202476 | E11: definitief (VC) | F11: 5885 | G11: 7538 | H11: extrapolatie datalaag | I11: =Parameters!$B$29 -> 55.7 | J11: =I11-Parameters!$B$27 -> 53.1 | K11: 134.56
A12: 2026 | B12: 17584903 | C12: schatting | D12: 219479 | E12: definitief | F12: 5914 | G12: 7514 | H12: extrapolatie datalaag | I12: =Parameters!$B$29 -> 55.7 | J12: =I12-Parameters!$B$27 -> 53.1
A14: Ingeschrevenen: Vektis/Zorgcijfersdatabank; 2025-2026 geschat (bevolking x ratio 2024). Nac-bedrag: NZa-indexatie; 2025 = voorcalculatie (afspraak 5). Praktijkhouders: Nivel t/m 2023.
A15: Winst: CBS StatLine 84467NED, zelfstandig ondernemers (huisartsen) met personeel - beste benadering van het praktijkhouderschap; dga-praktijkhouders vallen buiten deze reeks. Fiscale winst voor belasting; loopt t/m 2023.

Sheet Berekening
A1: De drie niveaus, per jaar - alles formules
A3: Jaar | B3: Deler: patienten per nac die de NZa terecht acht | C3: Nac's terecht geacht | D3: Deler: patienten per nac in de basistarieven | E3: Nac's in de basistarieven | F3: Aansluiting Cijfer-Meester | G3: Aandeel tarief-gereguleerd | H3: Nac-equivalent uit gereguleerde tarieven | I3: EUR terecht geacht | J3: EUR in de basistarieven | K3: EUR uit gereguleerd | L3: Gewerkte uren landelijk (excl. dienst) | M3: Per uur: terecht geacht | N3: Per uur: in de basistarieven | O3: Per uur: uit gereguleerd | P3: Per uur, prijspeil 2015 (basistarieven) | Q3: Gerealiseerde winst per gewerkt uur (gemiddeld) | R3: Gerealiseerde winst per gewerkt uur (mediaan)
A4: 2018 | B4: =IF(A4*1<=2024,Parameters!$B$5,Parameters!$B$15) -> 2095 | C4: =Reeksen!B4/B4 -> 8052.6697 | D4: =IF(A4*1<=2024,Parameters!$B$5,Parameters!$B$19) -> 2095 | E4: =Reeksen!B4/D4 -> 8052.6697 | F4: =E4/Reeksen!F4-1 -> 8.3170608e-05 | G4: =IF(A4*1<=2024,Parameters!$B$6,Parameters!$B$20) -> 0.7726 | H4: =E4*G4 -> 6221.4926 | I4: =C4*Reeksen!D4 -> 1.0903087e+09 | J4: =E4*Reeksen!D4 -> 1.0903087e+09 | K4: =H4*Reeksen!D4 -> 8.4237247e+08 | L4: =Reeksen!G4*Reeksen!J4*Parameters!$B$26 -> 16868163 | M4: =I4/L4 -> 64.637071 | N4: =J4/L4 -> 64.637071 | O4: =K4/L4 -> 49.938601 | P4: =IF(Reeksen!K4="","",N4*100/Reeksen!K4) -> 62.487501 | Q4: =IF(Reeksen!L4="","",Reeksen!L4/(Reeksen!I4*Parameters!$B$26)) -> 63.265306 | R4: =IF(Reeksen!M4="","",Reeksen!M4/(Reeksen!I4*Parameters!$B$26)) -> 59.405501
A5: 2019 | B5: =IF(A5*1<=2024,Parameters!$B$5,Parameters!$B$15) -> 2095 | C5: =Reeksen!B5/B5 -> 8107.5427 | D5: =IF(A5*1<=2024,Parameters!$B$5,Parameters!$B$19) -> 2095 | E5: =Reeksen!B5/D5 -> 8107.5427 | F5: =E5/Reeksen!F5-1 -> 6.694471e-05 | G5: =IF(A5*1<=2024,Parameters!$B$6,Parameters!$B$20) -> 0.7726 | H5: =E5*G5 -> 6263.8875 | I5: =C5*Reeksen!D5 -> 1.135281e+09 | J5: =E5*Reeksen!D5 -> 1.135281e+09 | K5: =H5*Reeksen!D5 -> 8.7711807e+08 | L5: =Reeksen!G5*Reeksen!J5*Parameters!$B$26 -> 17209748 | M5: =I5/L5 -> 65.96732 | N5: =J5/L5 -> 65.96732 | O5: =K5/L5 -> 50.966352 | P5: =IF(Reeksen!K5="","",N5*100/Reeksen!K5) -> 62.139525 | Q5: =IF(Reeksen!L5="","",Reeksen!L5/(Reeksen!I5*Parameters!$B$26)) -> 65.668483 | R5: =IF(Reeksen!M5="","",Reeksen!M5/(Reeksen!I5*Parameters!$B$26)) -> 61.504563
A6: 2020 | B6: =IF(A6*1<=2024,Parameters!$B$5,Parameters!$B$15) -> 2095 | C6: =Reeksen!B6/B6 -> 8133.4721 | D6: =IF(A6*1<=2024,Parameters!$B$5,Parameters!$B$19) -> 2095 | E6: =Reeksen!B6/D6 -> 8133.4721 | F6: =E6/Reeksen!F6-1 -> 5.8044556e-05 | G6: =IF(A6*1<=2024,Parameters!$B$6,Parameters!$B$20) -> 0.7726 | H6: =E6*G6 -> 6283.9205 | I6: =C6*Reeksen!D6 -> 1.1762681e+09 | J6: =E6*Reeksen!D6 -> 1.1762681e+09 | K6: =H6*Reeksen!D6 -> 9.0878474e+08 | L6: =Reeksen!G6*Reeksen!J6*Parameters!$B$26 -> 17005522 | M6: =I6/L6 -> 69.169774 | N6: =J6/L6 -> 69.169774 | O6: =K6/L6 -> 53.440567 | P6: =IF(Reeksen!K6="","",N6*100/Reeksen!K6) -> 64.33799 | Q6: =IF(Reeksen!L6="","",Reeksen!L6/(Reeksen!I6*Parameters!$B$26)) -> 69.889416 | R6: =IF(Reeksen!M6="","",Reeksen!M6/(Reeksen!I6*Parameters!$B$26)) -> 65.094332
A7: 2021 | B7: =IF(A7*1<=2024,Parameters!$B$5,Parameters!$B$15) -> 2095 | C7: =Reeksen!B7/B7 -> 8179.5499 | D7: =IF(A7*1<=2024,Parameters!$B$5,Parameters!$B$19) -> 2095 | E7: =Reeksen!B7/D7 -> 8179.5499 | F7: =E7/Reeksen!F7-1 -> 6.7230795e-05 | G7: =IF(A7*1<=2024,Parameters!$B$6,Parameters!$B$20) -> 0.7726 | H7: =E7*G7 -> 6319.5202 | I7: =C7*Reeksen!D7 -> 1.2067088e+09 | J7: =E7*Reeksen!D7 -> 1.2067088e+09 | K7: =H7*Reeksen!D7 -> 9.3230325e+08 | L7: =Reeksen!G7*Reeksen!J7*Parameters!$B$26 -> 17365138 | M7: =I7/L7 -> 69.490311 | N7: =J7/L7 -> 69.490311 | O7: =K7/L7 -> 53.688214 | P7: =IF(Reeksen!K7="","",N7*100/Reeksen!K7) -> 62.949824 | Q7: =IF(Reeksen!L7="","",Reeksen!L7/(Reeksen!I7*Parameters!$B$26)) -> 69.266226 | R7: =IF(Reeksen!M7="","",Reeksen!M7/(Reeksen!I7*Parameters!$B$26)) -> 63.784727
A8: 2022 | B8: =IF(A8*1<=2024,Parameters!$B$5,Parameters!$B$15) -> 2095 | C8: =Reeksen!B8/B8 -> 8221.9265 | D8: =IF(A8*1<=2024,Parameters!$B$5,Parameters!$B$19) -> 2095 | E8: =Reeksen!B8/D8 -> 8221.9265 | F8: =E8/Reeksen!F8-1 -> 0.00011269817 | G8: =IF(A8*1<=2024,Parameters!$B$6,Parameters!$B$20) -> 0.7726 | H8: =E8*G8 -> 6352.2604 | I8: =C8*Reeksen!D8 -> 1.2665734e+09 | J8: =E8*Reeksen!D8 -> 1.2665734e+09 | K8: =H8*Reeksen!D8 -> 9.7855462e+08 | L8: =Reeksen!G8*Reeksen!J8*Parameters!$B$26 -> 17749052 | M8: =I8/L8 -> 71.360061 | N8: =J8/L8 -> 71.360061 | O8: =K8/L8 -> 55.132783 | P8: =IF(Reeksen!K8="","",N8*100/Reeksen!K8) -> 58.766418 | Q8: =IF(Reeksen!L8="","",Reeksen!L8/(Reeksen!I8*Parameters!$B$26)) -> 64.481505 | R8: =IF(Reeksen!M8="","",Reeksen!M8/(Reeksen!I8*Parameters!$B$26)) -> 59.114823
A9: 2023 | B9: =IF(A9*1<=2024,Parameters!$B$5,Parameters!$B$15) -> 2095 | C9: =Reeksen!B9/B9 -> 8272.073 | D9: =IF(A9*1<=2024,Parameters!$B$5,Parameters!$B$19) -> 2095 | E9: =Reeksen!B9/D9 -> 8272.073 | F9: =E9/Reeksen!F9-1 -> 8.8287024e-06 | G9: =IF(A9*1<=2024,Parameters!$B$6,Parameters!$B$20) -> 0.7726 | H9: =E9*G9 -> 6391.0036 | I9: =C9*Reeksen!D9 -> 1.3553438e+09 | J9: =E9*Reeksen!D9 -> 1.3553438e+09 | K9: =H9*Reeksen!D9 -> 1.0471386e+09 | L9: =Reeksen!G9*Reeksen!J9*Parameters!$B$26 -> 18078956 | M9: =I9/L9 -> 74.968034 | N9: =J9/L9 -> 74.968034 | O9: =K9/L9 -> 57.920303 | P9: =IF(Reeksen!K9="","",N9*100/Reeksen!K9) -> 59.455971 | Q9: =IF(Reeksen!L9="","",Reeksen!L9/(Reeksen!I9*Parameters!$B$26)) -> 69.144614 | R9: =IF(Reeksen!M9="","",Reeksen!M9/(Reeksen!I9*Parameters!$B$26)) -> 64.245543
A10: 2024 | B10: =IF(A10*1<=2024,Parameters!$B$5,Parameters!$B$15) -> 2095 | C10: =Reeksen!B10/B10 -> 8305.2062 | D10: =IF(A10*1<=2024,Parameters!$B$5,Parameters!$B$19) -> 2095 | E10: =Reeksen!B10/D10 -> 8305.2062 | F10: =E10/Reeksen!F10-1 -> 2.4829049e-05 | G10: =IF(A10*1<=2024,Parameters!$B$6,Parameters!$B$20) -> 0.7726 | H10: =E10*G10 -> 6416.6023 | I10: =C10*Reeksen!D10 -> 1.4279947e+09 | J10: =E10*Reeksen!D10 -> 1.4279947e+09 | K10: =H10*Reeksen!D10 -> 1.1032687e+09 | L10: =Reeksen!G10*Reeksen!J10*Parameters!$B$26 -> 18441630 | M10: =I10/L10 -> 77.433213 | N10: =J10/L10 -> 77.433213 | O10: =K10/L10 -> 59.8249 | P10: =IF(Reeksen!K10="","",N10*100/Reeksen!K10) -> 59.422311 | Q10: =IF(Reeksen!L10="","",Reeksen!L10/(Reeksen!I10*Parameters!$B$26)) | R10: =IF(Reeksen!M10="","",Reeksen!M10/(Reeksen!I10*Parameters!$B$26))
A11: 2025 | B11: =IF(A11*1<=2024,Parameters!$B$5,Parameters!$B$15) -> 2650 | C11: =Reeksen!B11/B11 -> 6603.5989 | D11: =IF(A11*1<=2024,Parameters!$B$5,Parameters!$B$19) -> 2972.1848 | E11: =Reeksen!B11/D11 -> 5887.7688 | F11: =E11/Reeksen!F11-1 -> 0.00047047589 | G11: =IF(A11*1<=2024,Parameters!$B$6,Parameters!$B$20) -> 0.744 | H11: =E11*G11 -> 4380.5 | I11: =C11*Reeksen!D11 -> 1.3370703e+09 | J11: =E11*Reeksen!D11 -> 1.1921319e+09 | K11: =H11*Reeksen!D11 -> 8.8694611e+08 | L11: =Reeksen!G11*Reeksen!J11*Parameters!$B$26 -> 18412319 | M11: =I11/L11 -> 72.618245 | N11: =J11/L11 -> 64.746428 | O11: =K11/L11 -> 48.171342 | P11: =IF(Reeksen!K11="","",N11*100/Reeksen!K11) -> 48.117143 | Q11: =IF(Reeksen!L11="","",Reeksen!L11/(Reeksen!I11*Parameters!$B$26)) | R11: =IF(Reeksen!M11="","",Reeksen!M11/(Reeksen!I11*Parameters!$B$26))
A12: 2026 | B12: =IF(A12*1<=2024,Parameters!$B$5,Parameters!$B$15) -> 2650 | C12: =Reeksen!B12/B12 -> 6635.8125 | D12: =IF(A12*1<=2024,Parameters!$B$5,Parameters!$B$19) -> 2972.1848 | E12: =Reeksen!B12/D12 -> 5916.4904 | F12: =E12/Reeksen!F12-1 -> 0.00042109958 | G12: =IF(A12*1<=2024,Parameters!$B$6,Parameters!$B$20) -> 0.744 | H12: =E12*G12 -> 4401.8688 | I12: =C12*Reeksen!D12 -> 1.4564215e+09 | J12: =E12*Reeksen!D12 -> 1.2985454e+09 | K12: =H12*Reeksen!D12 -> 9.6611777e+08 | L12: =Reeksen!G12*Reeksen!J12*Parameters!$B$26 -> 18353696 | M12: =I12/L12 -> 79.353033 | N12: =J12/L12 -> 70.751164 | O12: =K12/L12 -> 52.638866 | P12: =IF(Reeksen!K12="","",N12*100/Reeksen!K12) | Q12: =IF(Reeksen!L12="","",Reeksen!L12/(Reeksen!I12*Parameters!$B$26)) | R12: =IF(Reeksen!M12="","",Reeksen!M12/(Reeksen!I12*Parameters!$B$26))
A14: Tot en met 2024 vallen niveau 1 en 2 samen: het 2015-model kortte de nac niet voor de 100%. Kolom F toont hoe de deling aansluit op de gepubliceerde reeks.
A15: Winst per uur deelt door de VOLLE werkweek (incl. dienst): in de gerealiseerde winst zitten ook de dienst- en overige inkomsten. De nac-kolommen delen door de werkweek exclusief dienst, omdat de nac dat werk niet dekt. Per persoon; geen landelijke optelling nodig.

Sheet Dekking
A1: Waar een hele nac vandaan moet komen - beide modellen op 100%
A3: Component | B3: Model 2015 | C3: Model 2022 | D3: Toelichting / vindplaats
A4: Uit tariefgereguleerde tarieven | B4: =Parameters!$B$6 -> 0.7726 | C4: =Parameters!$B$18*Parameters!$B$20 -> 0.6633504 | D4: 2015: tabel 33. 2022: binnen-100% x aandeel gereguleerd
A5: Uit niet-gereguleerde omzet binnen de 100% | B5: =Parameters!$B$7 -> 0.2274 | C5: =Parameters!$B$18*(1-Parameters!$B$20) -> 0.2282496 | D5: 2015: S2 11,07 + poh-s 3,33 + vrij 8,33 (griepprik c.s. zat in "vrij"). 2022: zorggroep 14,6 + S3 9,8 + M&I 1,6 (tabel 4.2.1.2)
A6: Buiten de 100% gezet (schoning) | B6: 0 | C6: =Parameters!$B$16 -> 0.0896 | D6: 2022: griepprik, bevolkingsonderzoek (incl. uitstrijkje), SBOH, verloskunde e.d. (par. 2.2.2, bijlage 8.2)
A7: Poh-ggz (managementtijd) | B7: 0 | C7: =Parameters!$B$17 -> 0.0188 | D7: 2015: alleen praktijkkosten gecorrigeerd, nac ongemoeid. 2022: uit de nac geschoond
A8: Som (hoort 100% te zijn) | B8: =SUM(B4:B7) -> 1 | C8: =SUM(C4:C7) -> 1 | D8: controle
A10: Kern: het niet-gereguleerde deel binnen de 100% bleef vrijwel gelijk (22,74% -> 22,82%), maar de samenstelling verschoof: griepprik c.s. ging eruit (naar buiten de 100%), gegroeide ketenzorg en S3 kwamen ervoor terug. De volledige daling van het gereguleerde aandeel (77,26% -> 66,34%) is de nieuw geexternaliseerde 10,84%.
A12: Uitgesloten voor het model (geen onderdeel van de 100%): 2015: poh-ggz, hds/anw, resultaatbeloning (omzet uitgesloten; alleen praktijkkosten poh-ggz gecorrigeerd). 2022: anw (uren buiten de fte-uitvraag; infra-correctie 3,5% bij declaratie buiten hds), vacatiegelden, achterstandsfonds, medicatiebeoordeling (bijlage 8.2).

Sheet Controle
A1: Controles - elke regel hoort (vrijwel) nul of gelijk te zijn
A3: Controle | B3: Berekend | C3: Gepubliceerd | D3: Verschil | E3: Vindplaats
A4: Tariefformule 2015: inschrijftarief = (nac+pkb) x 33,89% / 2.095 | B4: =(Parameters!$B$8+Parameters!$B$9)*0.3389/Parameters!$B$5 -> 50.215598 | C4: 50.21 | D4: =B4-C4 -> 0.0055975656 | E4: PKO 2015, tabel 34 en 33
A5: Tariefformule 2015: consulttarief = (nac+pkb) x 26,28% / 8.966 | B5: =(Parameters!$B$8+Parameters!$B$9)*0.2628/Parameters!$B$10 -> 9.0986659 | C5: 9.1 | D5: =B5-C5 -> -0.001334062 | E5: PKO 2015, tabel 34 en 33
A6: Deler-identiteit: 2.650 / binnen-100% (site) vs ingeschrevenen/gepubliceerd (Cijfer-Meester, 2025) | B6: =Parameters!$B$19 -> 2972.1848 | C6: =Reeksen!B11/Reeksen!F11 -> 2973.5832 | D6: =B6/C6-1 -> -0.00047025465 | E6: dezelfde deling, anders afgerond
A7: Grootste afwijking van de gepubliceerde reeks (alle jaren) | B7: =MAX(ABS(Berekening!F4),ABS(Berekening!F5),ABS(Berekening!F6),ABS(Berekening!F7),ABS(Berekening!F8),ABS(Berekening!F9),ABS(Berekening!F10),ABS(Berekening!F11),ABS(Berekening!F12)) -> 0.00047047589 | C7: 0.001 | D7: =B7-C7 -> -0.00052952411 | E7: norm: kleiner dan 0,1%
A8: Weging-alternatief: inschrijvingenweging zou 2.764 p/fte geven (4.477/1,62); afwijking t.o.v. gehanteerde 2.650 | B8: =4477/1.62 -> 2763.5802 | C8: =Parameters!$B$15 -> 2650 | D8: =B8/C8-1 -> 0.042860471 | E8: PKO 2022 tabel 4.2.2.1/4.2.6.1; afspraak 3: verantwoording volgen
A10: DE KNIK 2024 -> 2025, ONTLEED (per gewerkt uur)
A11: Per uur in de basistarieven, 2024 | B11: =Berekening!N10 -> 77.433213
A12: Per uur in de basistarieven, 2025 | B12: =Berekening!N11 -> 64.746428
A13: Knik totaal | B13: =B12-B11 -> -12.686785
A14: waarvan: minder nac's terecht geacht (2.095 -> 2.650) | B14: =Berekening!M11-B11 -> -4.8149677
A15: waarvan: verplaatst naar andere bekostiging (schoning + poh-ggz) | B15: =B12-Berekening!M11 -> -7.8718178
A16: Controle: som van de delen minus de knik | B16: =B14+B15-B13 -> 0
A18: Let op: "verplaatst" betekent dat de NZa dit deel elders vergoed acht (andere bekostiging en vrije omzet, o.b.v. omzet-evenredigheid) - niet dat elke praktijk het daar ook ontvangt.
